<?xml version="1.0" encoding="UTF-8"?>
<!DOCTYPE appendix [
<!ENTITY % constants SYSTEM "constants.ent" >
%constants;
]>

<appendix xml:id="license" xmlns="http://docbook.org/ns/docbook" xmlns:xlink="http://www.w3.org/1999/xlink" version="5.0">
 <title>License terms</title>
  <para>
    <mediaobject>
      <imageobject>
        <imagedata fileref="images/cc-by-sa.png" format="png" />
      </imageobject>
    </mediaobject>
  </para>
  <para>
    &PRODUCTNAME; by &COMPANY_ABBR; is licensed under a 
    <link xlink:href="http://creativecommons.org/licenses/by-sa/3.0/">
      <emphasis role="bold">Creative Commons Attribution-Share Alike 3.0 License</emphasis>
    </link>.
  </para>
  <para>
    Permissions beyond the scope of this license may be available at 
    <link xlink:href="http://jpos.org/contact?p=cmf">&COMPANY_ABBR;</link>.   
  </para>
</appendix>
